CHANGES.rst
MANIFEST.in
README.rst
poke_jenkins.py
setup.py
poke_jenkins.egg-info/PKG-INFO
poke_jenkins.egg-info/SOURCES.txt
poke_jenkins.egg-info/dependency_links.txt
poke_jenkins.egg-info/requires.txt
poke_jenkins.egg-info/top_level.txt