Metadata-Version: 1.0
Name: poke-jenkins
Version: 1.1.1
Summary: Mercurial extension to start new Jenkins jobs.
Home-page: https://github.com/paylogic/poke-jenkins
Author: Paylogic International
Author-email: developers@paylogic.com
License: MIT
Keywords: mercurial hg scm jenkins
Platform: UNKNOWN
